[
    {
      "inputs": [],
      "stateMutability": "payable",
      "type": "constructor"
    },
    {
      "anonymous": false,
      "inputs": [
        {
          "indexed": true,
          "internalType": "address",
          "name": "sellerAddress",
          "type": "address"
        },
        {
          "indexed": false,
          "internalType": "uint256",
          "name": "price",
          "type": "uint256"
        },
        {
          "indexed": false,
          "internalType": "uint256",
          "name": "roomNumber",
          "type": "uint256"
        }
      ],
      "name": "SellPosted",
      "type": "event"
    },
    {
      "anonymous": false,
      "inputs": [
        {
          "indexed": true,
          "internalType": "address",
          "name": "seller",
          "type": "address"
        },
        {
          "indexed": true,
          "internalType": "address",
          "name": "buyer",
          "type": "address"
        },
        {
          "indexed": false,
          "internalType": "uint256",
          "name": "price",
          "type": "uint256"
        },
        {
          "indexed": false,
          "internalType": "uint256",
          "name": "roomNumber",
          "type": "uint256"
        }
      ],
      "name": "TransferSuccess",
      "type": "event"
    },
    {
      "inputs": [
        {
          "internalType": "uint256",
          "name": "_roomNumber",
          "type": "uint256"
        }
      ],
      "name": "buy",
      "outputs": [],
      "stateMutability": "payable",
      "type": "function"
    },
    {
      "inputs": [],
      "name": "roomCount",
      "outputs": [
        {
          "internalType": "uint256",
          "name": "count",
          "type": "uint256"
        }
      ],
      "stateMutability": "view",
      "type": "function"
    },
    {
      "inputs": [
        {
          "internalType": "uint256",
          "name": "_roomNumber",
          "type": "uint256"
        }
      ],
      "name": "roomInfo",
      "outputs": [
        {
          "internalType": "enum TransferWhaleNFT.TradeStatus",
          "name": "",
          "type": "uint8"
        },
        {
          "internalType": "address",
          "name": "",
          "type": "address"
        },
        {
          "internalType": "uint256",
          "name": "",
          "type": "uint256"
        },
        {
          "internalType": "uint256",
          "name": "",
          "type": "uint256"
        }
      ],
      "stateMutability": "view",
      "type": "function"
    },
    {
      "inputs": [
        {
          "internalType": "address",
          "name": "_nftContract",
          "type": "address"
        },
        {
          "internalType": "uint256",
          "name": "_tokenId",
          "type": "uint256"
        },
        {
          "internalType": "uint256",
          "name": "_price",
          "type": "uint256"
        }
      ],
      "name": "sell",
      "outputs": [
        {
          "internalType": "uint256",
          "name": "roomNum",
          "type": "uint256"
        }
      ],
      "stateMutability": "nonpayable",
      "type": "function"
    }
]